odoo/addons/stock_release_channel_plan_shipment_lead_time/README.rst
odoo/addons/stock_release_channel_plan_shipment_lead_time/__init__.py
odoo/addons/stock_release_channel_plan_shipment_lead_time/__manifest__.py
odoo/addons/stock_release_channel_plan_shipment_lead_time/i18n/it.po
odoo/addons/stock_release_channel_plan_shipment_lead_time/i18n/stock_release_channel_plan_shipment_lead_time.pot
odoo/addons/stock_release_channel_plan_shipment_lead_time/models/__init__.py
odoo/addons/stock_release_channel_plan_shipment_lead_time/models/res_partner.py
odoo/addons/stock_release_channel_plan_shipment_lead_time/models/stock_release_channel.py
odoo/addons/stock_release_channel_plan_shipment_lead_time/readme/CONTRIBUTORS.md
odoo/addons/stock_release_channel_plan_shipment_lead_time/readme/DESCRIPTION.md
odoo/addons/stock_release_channel_plan_shipment_lead_time/static/description/icon.png
odoo/addons/stock_release_channel_plan_shipment_lead_time/static/description/index.html
odoo/addons/stock_release_channel_plan_shipment_lead_time/tests/__init__.py
odoo/addons/stock_release_channel_plan_shipment_lead_time/tests/test_lead_time_weekday.py
odoo/addons/stock_release_channel_plan_shipment_lead_time/views/release_channel.xml
odoo_addon_stock_release_channel_plan_shipment_lead_time-18.0.1.0.1.dist-info/METADATA
odoo_addon_stock_release_channel_plan_shipment_lead_time-18.0.1.0.1.dist-info/WHEEL
odoo_addon_stock_release_channel_plan_shipment_lead_time-18.0.1.0.1.dist-info/top_level.txt
odoo_addon_stock_release_channel_plan_shipment_lead_time-18.0.1.0.1.dist-info/RECORD
