Metadata-Version: 2.1
Name: odoo-addon-stock_release_channel_plan_shipment_lead_time
Version: 18.0.1.0.1
Requires-Python: >=3.10
Requires-Dist: odoo-addon-stock_release_channel_plan==18.0.*
Requires-Dist: odoo-addon-stock_release_channel_shipment_lead_time==18.0.*
Requires-Dist: odoo==18.0.*
Summary: Stock release channel plan shipment lead time
Home-page: https://github.com/OCA/stock-logistics-release-channel
License: AGPL-3
Author: Camptocamp, BCIM, Odoo Community Association (OCA)
Author-email: support@odoo-community.org
Classifier: Programming Language :: Python
Classifier: Framework :: Odoo
Classifier: Framework :: Odoo :: 18.0
Classifier: License :: OSI Approved :: GNU Affero General Public License v3
Classifier: Development Status :: 4 - Beta
